README.md
setup.py
delta_lake/Bronze.py
delta_lake/DataLake.py
delta_lake/Gold.py
delta_lake/Silver.py
delta_lake/Util.py
delta_lake/__init__.py
delta_lake/const.py
delta_lake/main.py
delta_lake/test/TestBronze.py
delta_lake/test/TestDataLake.py
delta_lake/test/TestSilver.py
delta_lake/test/__init__.py
delta_lake/test/TestBronze.py
delta_lake/test/TestDataLake.py
delta_lake/test/TestSilver.py
delta_lake/test/__init__.py
test_data_lake.egg-info/PKG-INFO
test_data_lake.egg-info/SOURCES.txt
test_data_lake.egg-info/dependency_links.txt
test_data_lake.egg-info/not-zip-safe
test_data_lake.egg-info/top_level.txt