Metadata-Version: 2.1
Name: test-data-lake
Version: 0.0.0.31
Summary: processes Datalake to Bronze-Silver_Gold
Home-page: https://upload.pypi.org/
Author: Imparnert
Author-email: alexander.grajales@devsavant.ai
License: MIT
Platform: UNKNOWN
Classifier: Programming Language :: Python :: 3
Requires-Python: >=3
